<?xml version="1.0" encoding="utf-8"?>
<ParsedDocxDocument xmlns:xsi="http://www.w3.org/2001/XMLSchema-instance" xmlns:xsd="http://www.w3.org/2001/XMLSchema">
  <WerkId>0035</WerkId>
  <WerkTitel>Annales Tiliani</WerkTitel>
  <Alternativtitel>
    <Titel>Annalen des Jean du Tillet</Titel>
    <Titel>Jahrbücher des Johannes Tilius</Titel>
    <Titel>Jahrbücher des Jean du Tillet</Titel>
  </Alternativtitel>
  <Autoren>
    <Autor>unbekannt</Autor>
  </Autoren>
  <LebensdatenVerfasser>unbekannt</LebensdatenVerfasser>
  <Abfassungszeitraum>unbekannt</Abfassungszeitraum>
  <Abfassungsort>unbekannt</Abfassungsort>
  <Regionen>
    <Region>West- und Mitteleuropa</Region>
  </Regionen>
  <Editionshinweise>Annales Tiliani, ed. Georg Heinrich Pertz, in: MGH SS 1, Hannover 1826, S. 6, 8, 219-224.</Editionshinweise>
  <Werkinformation>Die Annales Tiliani sind nach dem ehemaligen Besitzer der Handschrift, Jean du Tillet (gest. 1570) benannt. Sie berichten über die Jahre 708 bis 807 und stammen aus derselben Vorlage wie die Annales S. Amandi (bis 737) bzw. haben für die jüngere Zeit die Annales regni Francorum zur Vorlage. Die handschriftliche Überlieferung ist heute verloren.
Vgl. mit Hinweisen für weiterführende Literatur: Annales Tiliani, in: Repertorium ‚Geschichtsquellen des deutschen Mittelalters‘ [http://www.geschichtsquellen.de/repOpus_00431.html, 2016-11-02].
---------------------------------------------------------------</Werkinformation>
  <Quellen>
    <Quelle>
      <QuellenId>0001</QuellenId>
      <Zitation>Annales Tiliani a. 732, ed. Pertz 1826, S. 8.</Zitation>
      <ZeitangabeQuelle>732</ZeitangabeQuelle>
      <Inhaltsangabe>Der fränkische Hausmeier Karl Martell führt 732 Krieg gegen die Sarazenen.</Inhaltsangabe>
      <VolltextOriginalsprache>Karolus [Karl Martell] bellum habuit contra Sarecinos.</VolltextOriginalsprache>
      <VolltextUebersetzung>-</VolltextUebersetzung>
      <ZitationUebersetzung>-</ZitationUebersetzung>
      <ZeitangabeWissenschaft>
        <Datum Text="732" From="732-01-01" To="732-12-31" />
      </ZeitangabeWissenschaft>
      <Berichtszeitraum>
        <Datum Text="730-740" From="730-01-01" To="740-12-31" />
      </Berichtszeitraum>
      <Abfassungszeitraum />
      <GeographischesStichwort>
        <Ort>Frankenreich (Deutschland, Frankreich)</Ort>
        <Ort>Poitiers</Ort>
      </GeographischesStichwort>
      <Beteiligte>
        <Beteiligter>sK</Beteiligter>
        <Beteiligter>aI</Beteiligter>
      </Beteiligte>
      <Interaktion>j</Interaktion>
      <Auffaelligkeiten>
        <Schlagwort>Kampfhandlung</Schlagwort>
      </Auffaelligkeiten>
      <Suchbegriffe>
        <Suchwort>Sarecinus</Suchwort>
        <Suchwort>Saracenus</Suchwort>
        <Suchwort>Sarazene</Suchwort>
      </Suchbegriffe>
      <Anmerkungen>Laut Nonn handelt es sich um die Schlacht bei Poitiers 732, in der Karl Martell die aus Spanien kommenden Sarazenen schlägt, vgl. Ulrich Nonn, Art. Karl Martell, frk. Hausmeier, in: Lexikon des Mittelalters 5, Sp. 954-956 [Brepolis Medieval Encyclopaedias – Lexikon des Mittelalters Online, 2017-08-31].</Anmerkungen>
      <Entitaeten>
        <Entitaet Id="b24a1eac-b648-44a2-81c3-8871d03a7906" Type="Person">
          <Name>Karl Martell</Name>
        </Entitaet>
      </Entitaeten>
    </Quelle>
    <Quelle>
      <QuellenId>0002</QuellenId>
      <Zitation>Annales Tiliani a. 737 (736), ed. Pertz 1826, S. 8.</Zitation>
      <ZeitangabeQuelle>737 (736)</ZeitangabeQuelle>
      <Inhaltsangabe>Der fränkische Hausmeier Karl Martell führt 737 (736) [737] Krieg gegen die Sarazenen.</Inhaltsangabe>
      <VolltextOriginalsprache>Karolus [Karl Martell] iterum habuit bellum contra Sarecinos.</VolltextOriginalsprache>
      <VolltextUebersetzung>-</VolltextUebersetzung>
      <ZitationUebersetzung>-</ZitationUebersetzung>
      <ZeitangabeWissenschaft>
        <Datum Text="737" From="737-01-01" To="737-12-31" />
      </ZeitangabeWissenschaft>
      <Berichtszeitraum>
        <Datum Text="730-740" From="730-01-01" To="740-12-31" />
      </Berichtszeitraum>
      <Abfassungszeitraum />
      <GeographischesStichwort>
        <Ort>Frankenreich (Deutschland, Frankreich)</Ort>
        <Ort>Avignon</Ort>
      </GeographischesStichwort>
      <Beteiligte>
        <Beteiligter>sK</Beteiligter>
        <Beteiligter>aI</Beteiligter>
      </Beteiligte>
      <Interaktion>j</Interaktion>
      <Auffaelligkeiten>
        <Schlagwort>Kampfhandlung</Schlagwort>
      </Auffaelligkeiten>
      <Suchbegriffe>
        <Suchwort>Sarecinus</Suchwort>
        <Suchwort>Saracenus</Suchwort>
        <Suchwort>Sarazene</Suchwort>
      </Suchbegriffe>
      <Anmerkungen>Die erneuten Kämpfe zwischen dem Hausmeier Karl Martell und den Sarazenen finden wahrscheinlich in Südfrankreich statt. Laut Nonn handelt sich dabei wahrscheinlich um die Schlachten bei Avignon und am Fluss Berre, vgl. Ulrich Nonn, Art. Karl Martell, frk. Hausmeier, in: Lexikon des Mittelalters 5, Sp. 954-956 [Brepolis Medieval Encyclopaedias – Lexikon des Mittelalters Online, 2017-08-31]; Ders., Die Schlacht bei Poitiers 732. Probleme historischer Urteilsbildung, in: Beiträge zur Geschichte des Regnum Francorum. Referate beim Wissenschaftlichen Colloquium zum 75. Geburtstag von Eugen Ewig, hg. von Rudolf Schieffer (Beiheft der Francia 22), Sigmaringen 1990, S. 37-56, hier: S. 40f.; Anne-Marie Hayez, Art. Avignon, I. Geschichte der Stadt und der Seigneurie, in: Lexikon des Mittelalters 1, Sp. 1301-1302 [Brepolis Medieval Encyclopaedias – Lexikon des Mittelalters Online, 2017-08-31].
Die Jahresangaben in runden Klammern beziehen sich wohl auf Unterschiede in der handschriftlichen Überlieferung, wie sie die Ausgabe von Andrea Chesnio vermittelt, vgl. Annales Tiliani, ed. Georg Heinrich Pertz, in: MGH SS 1, Hannover 1826, S. 220. Die handschriftliche Überlieferung ist verloren.</Anmerkungen>
      <Entitaeten>
        <Entitaet Id="b24a1eac-b648-44a2-81c3-8871d03a7906" Type="Person">
          <Name>Karl Martell</Name>
        </Entitaet>
      </Entitaeten>
    </Quelle>
    <Quelle>
      <QuellenId>0003</QuellenId>
      <Zitation>Annales Tiliani pars altera a. 778 (779), ed. Pertz 1826, S. 220f.</Zitation>
      <ZeitangabeQuelle>778 (779)</ZeitangabeQuelle>
      <Inhaltsangabe>Karl der Große begibt sich 777 (778) [777/778] auf zwei Wegen nach Spanien. Einer führt über Pamplona nach Saragosssa, wo er Geiseln von Ibin al Arabi [Statthalter von Saragossa?] und Abutauro [Wali Abu Tawr von Huesca] in Gewahrsam nimmt, nachdem Pamplona zerstört worden war. Er unterwirft die Spanier und Wasconen und kehrt ins Frankenreich zurück.</Inhaltsangabe>
      <VolltextOriginalsprache>Tunc domnus imperator [Karl I. der Große] agens partibus Hispaniae [Spanien] per duas vias; una per Pampaloniam [Pamplona], per quem ipse perrexit usque Caesaraugustam [Saragossa]: ibi obsides receptos de Ibinalarabi [Ibin al Arabi] et de Abutauro [Wali Abu Tawr von Huesca], Pampalonia [Pamplona] destructa, Hispanos Wascones subiugatos, reversus est in Franciam [Frankenreich].</VolltextOriginalsprache>
      <VolltextUebersetzung>-</VolltextUebersetzung>
      <ZitationUebersetzung>-</ZitationUebersetzung>
      <ZeitangabeWissenschaft>
        <Datum Text="777/778" From="777-01-01" To="777-12-31" />
        <Datum Text="777/778" From="778-01-01" To="778-12-31" />
      </ZeitangabeWissenschaft>
      <Berichtszeitraum>
        <Datum Text="770-780" From="770-01-01" To="780-12-31" />
      </Berichtszeitraum>
      <Abfassungszeitraum />
      <GeographischesStichwort>
        <Ort>Iberische Halbinsel (Spanien, Portugal)</Ort>
        <Ort>Pamplona</Ort>
        <Ort>Saragossa</Ort>
        <Ort>Frankenreich (Deutschland, Frankreich)</Ort>
      </GeographischesStichwort>
      <Beteiligte>
        <Beteiligter>sI</Beteiligter>
        <Beteiligter>sK</Beteiligter>
        <Beteiligter>aI</Beteiligter>
      </Beteiligte>
      <Interaktion>j</Interaktion>
      <Auffaelligkeiten>
        <Schlagwort>Heeresaufgebot</Schlagwort>
        <Schlagwort>Unterwerfung</Schlagwort>
        <Schlagwort>Gefangennahme</Schlagwort>
        <Schlagwort>Zerstörung</Schlagwort>
      </Auffaelligkeiten>
      <Suchbegriffe>
        <Suchwort>Ibin</Suchwort>
        <Suchwort>Hispania</Suchwort>
        <Suchwort>Spanien</Suchwort>
        <Suchwort>Caesaraugusta</Suchwort>
        <Suchwort>Saragossa</Suchwort>
      </Suchbegriffe>
      <Anmerkungen>Laut Vones handelt sich bei dem beschriebenen Zug nach Spanien um das Vorgehen Karls des Großen gegen die Sarazenen in den Jahren 777-778, vgl. Ludwig Vones, Zwischen Expansion und Kulturkontakt. Karl der Grosse und das muslimische Spanien, in: Ex Oriente: Isaak und der weisse Elefant. Bagdad-Jerusalem-Aachen: Eine Reise durch drei Kulturen um 800 und heute, Bd. 3: Aachen. Der Westen, hg. von Wolfgang Dreßen (Geschichte und Gegenwart christlicher, jüdischer und islamischer Kulturen), Mainz 2003, S. 94-99, hier S. 94ff. Vgl. auch Josef Fleckenstein, Art. Karl (I.) der Große, A. Leben und Persönlichkeit, 2. Feldzüge gegen das islamische Spanien, in: Lexikon des Mittelalters 5, Sp. 956-957 [Brepolis Medieval Encyclopaedias – Lexikon des Mittelalters Online, 2017-08-31].
Die Jahresangaben in runden Klammern beziehen sich wohl auf Unterschiede in der handschriftlichen Überlieferung, wie sie die Ausgabe von Andrea Chesnio vermittelt, vgl. Annales Tiliani, ed. Georg Heinrich Pertz, in: MGH SS 1, Hannover 1826, S. 220. Die handschriftliche Überlieferung ist verloren gegangen.</Anmerkungen>
      <Entitaeten>
        <Entitaet Id="9531e20f-d30b-4606-8f64-d587c1c9d7fd" Type="Person">
          <Name>Karl I. der Große</Name>
        </Entitaet>
        <Entitaet Id="1b3bc365-6179-45d1-b0bd-21aab4abd3e3" Type="Ort">
          <Name>Spanien</Name>
        </Entitaet>
        <Entitaet Id="8c6acf1b-8f06-4af6-9398-9f7f2bc2833f" Type="Ort">
          <Name>Pamplona</Name>
        </Entitaet>
        <Entitaet Id="7df93b79-4411-4b80-86ad-d626c1003bbe" Type="Ort">
          <Name>Saragossa</Name>
        </Entitaet>
        <Entitaet Id="4b8f6440-a20c-4870-98a7-b19e10e563ca" Type="Person">
          <Name>Ibin al Arabi</Name>
        </Entitaet>
        <Entitaet Id="a09e20d5-0ab2-470b-9890-8a40b9d3d040" Type="Person">
          <Name>Wali Abu Tawr von Huesca</Name>
        </Entitaet>
        <Entitaet Id="776d9240-2902-42ea-bf0f-08cdfecd4a76" Type="Ort">
          <Name>Frankenreich</Name>
        </Entitaet>
      </Entitaeten>
    </Quelle>
    <Quelle>
      <QuellenId>0004</QuellenId>
      <Zitation>Annales Tiliani pars altera 797 (798), ed. Pertz 1826, S. 222.</Zitation>
      <ZeitangabeQuelle>797 (798)</ZeitangabeQuelle>
      <Inhaltsangabe>Der Statthalter Sa’dun al-Ru’aini von Barcelona kommt 797 (798) [798] zur Pfalz König Karls I. des Großen und unterwirft sich und seine Stadt dessen Herrschaft. Außerdem empfängt Karl den Sarazenen Abdellah, Sohn des Kalifen Abd ar-Rahman I. von Cordoba, nachdem er von seinem Bruder von der Herrschaft ausgeschlossen und nach Mauretanien verbannt worden war. Abdellah unterwirft sich Karl. Daraufhin kehrt er mit Karls Sohn, Ludwig I. der Fromme, nach Spanien zurück.</Inhaltsangabe>
      <VolltextOriginalsprache>Barcilona [Barcelona] civitas Hispaniae [Spanien], quae iampridem a nobis descierat, per Zatum [Sa’dun al-Ru’aini] praefectum ipsius nobis est reddita; nam ipse ad palatium veniens, domno regi [Karl I. der Große] semetipsum cum civitate commendavit. […] et in Aquis [Aachen] palatio Adabdellam [Abdellah] Saracenum, filium Ibin-Mauge regis [Emir Abd ar-Rahman I.], qui a fratre regno [Hisham I.] pulsus in Mauritania [Mauretanien] exulabat, ipso semetipsum commendante, suscepit. […], inde Adabdellam Saracenum cum filio suo Hluduico [Ludwig I. der Fromme] in Hispania [Spanien] reverti fecit […].</VolltextOriginalsprache>
      <VolltextUebersetzung>-</VolltextUebersetzung>
      <ZitationUebersetzung>-</ZitationUebersetzung>
      <ZeitangabeWissenschaft>
        <Datum Text="798" From="798-01-01" To="798-12-31" />
      </ZeitangabeWissenschaft>
      <Berichtszeitraum>
        <Datum Text="790-800" From="790-01-01" To="800-12-31" />
      </Berichtszeitraum>
      <Abfassungszeitraum />
      <GeographischesStichwort>
        <Ort>Iberische Halbinsel (Spanien, Portugal)</Ort>
        <Ort>Barcelona</Ort>
        <Ort>Mauretanien</Ort>
        <Ort>Frankenreich (Deutschland, Frankreich)</Ort>
      </GeographischesStichwort>
      <Beteiligte>
        <Beteiligter>sI</Beteiligter>
        <Beteiligter>sK</Beteiligter>
        <Beteiligter>aI</Beteiligter>
      </Beteiligte>
      <Interaktion>j</Interaktion>
      <Auffaelligkeiten>
        <Schlagwort>Gesandtschaft</Schlagwort>
        <Schlagwort>Unterwerfung</Schlagwort>
        <Schlagwort>Thronstreit</Schlagwort>
        <Schlagwort>Würdigung</Schlagwort>
        <Schlagwort>Verbannung</Schlagwort>
      </Auffaelligkeiten>
      <Suchbegriffe>
        <Suchwort>Saracenus</Suchwort>
        <Suchwort>Sarazenen</Suchwort>
        <Suchwort>Ibin</Suchwort>
        <Suchwort>Hispania</Suchwort>
        <Suchwort>Spanien</Suchwort>
        <Suchwort>Barcelona</Suchwort>
        <Suchwort>Mauritania</Suchwort>
        <Suchwort>Mauretanien</Suchwort>
      </Suchbegriffe>
      <Anmerkungen>Abdellahs Hilfegesuch am kaiserlichen Hof steht in Verbindung mit dem Tod seines Bruders, Hisham I. (788-796), Sohn des Abd ar-Rahman I. (756-788), dem er während seiner Regierungszeit in offener Rebellion gegenüberstand. Im Zuge der Machtübernahme seines Neffen, al-Hakam I. (796-822), Sohn Hishams I., bat Abdellah König Karl den Großen in seiner Pfalz um Hilfe.
Die genannte Unterwerfung Abdellahs, der gemeinsam mit Karls Sohn Ludwig I. dem Frommen aus der Pfalz abreiste, steht nach Collins in Zusammenhang mit weiteren Quellenstellen: Der wahrscheinlich gleichzeitig stattfindenden Plünderung von Lissabon (vgl. [0035]-[0005]) und der Einnahme von Barcelona 801 (vgl. [0035]-[0006]). Vgl. Roger Collins, The Arab Conquest of Spain. 710-797, Oxford 1989, S. 210-216, sowie Josef Fleckenstein, Art. Karl (I.) der Große, A. Leben und Persönlichkeit, 2. Feldzüge gegen das islamische Spanien, in: Lexikon des Mittelalters 5, Sp. 956-957 [Brepolis Medieval Encyclopaedias – Lexikon des Mittelalters Online, 2017-08-31].
Die Jahresangaben in runden Klammern beziehen sich wohl auf Unterschiede in der handschriftlichen Überlieferung, wie sie die Ausgabe von Andrea Chesnio vermittelt, vgl. Annales Tiliani, ed. Georg Heinrich Pertz, in: MGH SS 1, Hannover 1826, S. 220. Die handschriftliche Überlieferung ist verloren.
Vgl. zu diesem Bericht auch: [0008]-[0013]; [0014]-[0003]; [0018]-[0004]; [0020]-[0001]; [0044]-[0004].</Anmerkungen>
      <Entitaeten>
        <Entitaet Id="75089f58-05c5-4d54-a13e-3adb94ba8635" Type="Ort">
          <Name>Barcelona</Name>
        </Entitaet>
        <Entitaet Id="1b3bc365-6179-45d1-b0bd-21aab4abd3e3" Type="Ort">
          <Name>Spanien</Name>
        </Entitaet>
        <Entitaet Id="08940327-0bb7-4b38-bbf6-3965d86ee28e" Type="Person">
          <Name>Sa’dun al-Ru’aini</Name>
        </Entitaet>
        <Entitaet Id="9531e20f-d30b-4606-8f64-d587c1c9d7fd" Type="Person">
          <Name>Karl I. der Große</Name>
        </Entitaet>
        <Entitaet Id="5a7f5157-8c7f-4146-a520-62dcf6a1efee" Type="Ort">
          <Name>Aachen</Name>
        </Entitaet>
        <Entitaet Id="b2fe319d-877e-49ea-9581-9bd883df6373" Type="Person">
          <Name>Abdellah</Name>
        </Entitaet>
        <Entitaet Id="f679dac4-68f1-4faa-af66-b3ceb1c21623" Type="Person">
          <Name>Emir Abd ar-Rahman I.</Name>
        </Entitaet>
        <Entitaet Id="5d034a50-5e38-4d49-b235-d680b249d7f7" Type="Person">
          <Name>Hisham I.</Name>
        </Entitaet>
        <Entitaet Id="7bd20aba-ffc4-403e-b1d8-d2256a7a8fcb" Type="Ort">
          <Name>Mauretanien</Name>
        </Entitaet>
        <Entitaet Id="43e564f2-a938-45b0-8bc8-ed2740fb9bf4" Type="Person">
          <Name>Ludwig I. der Fromme</Name>
        </Entitaet>
      </Entitaeten>
    </Quelle>
    <Quelle>
      <QuellenId>0005</QuellenId>
      <Zitation>Annales Tiliani pars altera 798 (799), ed. Pertz 1826, S. 222.</Zitation>
      <ZeitangabeQuelle>798 (799)</ZeitangabeQuelle>
      <Inhaltsangabe>König Alfons II. der Keusche von Asturien schickt 798 (799) [797/798], nachdem er Lissabon im Winter erobert hat, Zeichen seines Sieges (Brustpanzer, Rüstungen und gefangene Mauren) an König Karl I. den Großen.</Inhaltsangabe>
      <VolltextOriginalsprache>Hadefonsus rex Galliciae et Asturiae [Alfons II.], praedata Olisipona [Lissabon] ultima Hispaniae [Spanien] civitate, insignia victoriae suae, loricas, mulos, captivosque Mauros domno regi [Karl I. der Große] per legatos suos hyemis tempore misit […].</VolltextOriginalsprache>
      <VolltextUebersetzung>-</VolltextUebersetzung>
      <ZitationUebersetzung>-</ZitationUebersetzung>
      <ZeitangabeWissenschaft>
        <Datum Text="797/98" From="797-01-01" To="797-12-31" />
        <Datum Text="797/98" From="799-01-01" To="799-12-31" />
      </ZeitangabeWissenschaft>
      <Berichtszeitraum>
        <Datum Text="790-800" From="790-01-01" To="800-12-31" />
      </Berichtszeitraum>
      <Abfassungszeitraum />
      <GeographischesStichwort>
        <Ort>Iberische Halbinsel (Spanien, Portugal)</Ort>
        <Ort>Asturien</Ort>
        <Ort>Lissabon</Ort>
        <Ort>Frankenreich (Deutschland, Frankreich)</Ort>
      </GeographischesStichwort>
      <Beteiligte>
        <Beteiligter>sK</Beteiligter>
        <Beteiligter>aI</Beteiligter>
      </Beteiligte>
      <Interaktion>n</Interaktion>
      <Auffaelligkeiten>
        <Schlagwort>Gesandtschaft</Schlagwort>
        <Schlagwort>Annäherung</Schlagwort>
        <Schlagwort>Gefangennahme</Schlagwort>
        <Schlagwort>Geschenke</Schlagwort>
        <Schlagwort>Eroberung</Schlagwort>
        <Schlagwort>Einnahme</Schlagwort>
        <Schlagwort>Sieg</Schlagwort>
      </Auffaelligkeiten>
      <Suchbegriffe>
        <Suchwort>Mauri</Suchwort>
        <Suchwort>Mauren</Suchwort>
        <Suchwort>Hispania</Suchwort>
        <Suchwort>Spanien</Suchwort>
      </Suchbegriffe>
      <Anmerkungen>Zur Geschichte des Königreichs Asturiens und der Gesandtschaft an den Hof Karls des Großen vgl. Klaus Herbers, Geschichte Spaniens im Mittelalter. Vom Westgotenreich bis zum Ende des 15. Jahrhunderts, Stuttgart 2006, S. 107.
Zu den diplomatischen Verbindung Alfons II. mit Karl dem Großen vgl. Claudio Sanchez-Albornoz, Origenes de la nacion Española. Estudios Criticos sobre la historia del reino de Asturias, Bd. 2, Oviedo 1974, S. 531-551.
Die Jahresangaben in runden Klammern beziehen sich wohl auf Unterschiede in der handschriftlichen Überlieferung, wie sie die Ausgabe von Andrea Chesnio vermittelt, vgl. Annales Tiliani, ed. Georg Heinrich Pertz, in: MGH SS 1, Hannover 1826, S. 220. Die handschriftliche Überlieferung ist verloren.</Anmerkungen>
      <Entitaeten>
        <Entitaet Id="ca2a6f99-57bd-489d-abc6-d69aa30d7094" Type="Person">
          <Name>Alfons II.</Name>
        </Entitaet>
        <Entitaet Id="1981f381-2e6b-47b2-b8dd-09f8af6c1f68" Type="Ort">
          <Name>Lissabon</Name>
        </Entitaet>
        <Entitaet Id="1b3bc365-6179-45d1-b0bd-21aab4abd3e3" Type="Ort">
          <Name>Spanien</Name>
        </Entitaet>
        <Entitaet Id="9531e20f-d30b-4606-8f64-d587c1c9d7fd" Type="Person">
          <Name>Karl I. der Große</Name>
        </Entitaet>
      </Entitaeten>
    </Quelle>
    <Quelle>
      <QuellenId>0006</QuellenId>
      <Zitation>Annales Tiliani pars altera 801 (802), ed. Pertz 1826, S. 223.</Zitation>
      <ZeitangabeQuelle>801 (802)</ZeitangabeQuelle>
      <Inhaltsangabe>Kaiser Karl I. der Große reist 801 (802) [801] nach Ravenna und von dort aus weiter nach Pavia, während eine Gesandtschaft des Kalifen Harun al-Raschid von Bagdad – bestehend aus einem Perser und einem aus dem sarazenischen Afrika stammenden Sarazenen –, die aus Pisa angereist ist, sich zu ihm auf den Weg macht. Die Gesandten ziehen Karl entgegen und treffen ihn zwischen Vercelli und Ivera. Karl schickt den Notar Erchenbald, um ein Schiff umzurüsten, welches den Elefanten Abul Abaz und seine Begleitung an seinen Hof bringen soll. […]</Inhaltsangabe>
      <VolltextOriginalsprache>Imperator [Karl I. der Große] de Spoleto [Spoleto] Ravennam [Ravenna] veniens, aliquot dies ibi moratus, Papiam [Pavia] perrexit, ibi nunciatum ei legatos Aaron Amiralmumminin, regis Persarum, [Kalif Harun al-Raschid] portum Pisas [Pisa] intrasse. Quibus obviam mittens, inter Vercellis [Vercelli] et Eporegiam [Ivrea] sibi fecit praesentari. Unus erat de Persa, legatus regis Persarum, alter de Africa [Afrika] Saracenus. Tunc ille misit Erchembaldum ad classem parandam, qua elifans [Abul Abaz] et ea quae deferebantur subveherentur, ipse rex celebravit diem sancti Iohannis baptistae, reversus est in Galliam [Gallien].</VolltextOriginalsprache>
      <VolltextUebersetzung>-</VolltextUebersetzung>
      <ZitationUebersetzung>-</ZitationUebersetzung>
      <ZeitangabeWissenschaft>
        <Datum Text="801" From="801-01-01" To="801-12-31" />
      </ZeitangabeWissenschaft>
      <Berichtszeitraum>
        <Datum Text="800-810" From="800-01-01" To="810-12-31" />
      </Berichtszeitraum>
      <Abfassungszeitraum />
      <GeographischesStichwort>
        <Ort>Italien</Ort>
        <Ort>Spoleto</Ort>
        <Ort>Ravenna</Ort>
        <Ort>Pisa</Ort>
        <Ort>Vercelli</Ort>
        <Ort>Ivera</Ort>
        <Ort>Umayyadisches Reich</Ort>
        <Ort>Afrika</Ort>
      </GeographischesStichwort>
      <Beteiligte>
        <Beteiligter>sI</Beteiligter>
        <Beteiligter>aI</Beteiligter>
      </Beteiligte>
      <Interaktion>j</Interaktion>
      <Auffaelligkeiten>
        <Schlagwort>Gesandtschaft</Schlagwort>
        <Schlagwort>Elefant</Schlagwort>
        <Schlagwort>Annäherung</Schlagwort>
      </Auffaelligkeiten>
      <Suchbegriffe>
        <Suchwort>Saracenus</Suchwort>
        <Suchwort>Sarazenen</Suchwort>
        <Suchwort>Aaron</Suchwort>
        <Suchwort>Persus</Suchwort>
        <Suchwort>Persien</Suchwort>
      </Suchbegriffe>
      <Anmerkungen>Vgl. für die Ereignisse RI I, 372a &amp; 374a.
Zur Reise Abul Abaz‘ vgl. Klaus Grewe – Frank Pohle, Der Weg des Abul Abaz von Bagdad nach Aachen, in: Ex Oriente: Isaak und der weisse Elefant. Bagdad-Jerusalem-Aachen, Bd. 1: Die Reise des Isaak, Bagdad, hg. Wolfgang Dreßen – Georg Minkenberg – Adam C. Oellers (Geschichte und Gegenwart christlicher, jüdischer und islamischer Kulturen), Mainz 2003, S. 66-69; sowie Achim Thomas Hack, Abul Abaz. Zur Biographie eines Elefanten, Badenweiler 2012, S. 22-27, mit einer Kritik am Routenverlauf der Karte von Grewe/Pohle.
Die Jahresangaben in runden Klammern beziehen sich wohl auf Unterschiede in der handschriftlichen Überlieferung, wie sie die Ausgabe von Andrea Chesnio vermittelt, vgl. Annales Tiliani, ed. Georg Heinrich Pertz, in: MGH SS 1, Hannover 1826, S. 220. Die handschriftliche Überlieferung ist verloren.</Anmerkungen>
      <Entitaeten>
        <Entitaet Id="9531e20f-d30b-4606-8f64-d587c1c9d7fd" Type="Person">
          <Name>Karl I. der Große</Name>
        </Entitaet>
        <Entitaet Id="341998e5-30c3-4a86-8bb8-80a38ce1df0c" Type="Ort">
          <Name>Spoleto</Name>
        </Entitaet>
        <Entitaet Id="e1504d41-9556-48de-8949-8ce4f72a5118" Type="Ort">
          <Name>Ravenna</Name>
        </Entitaet>
        <Entitaet Id="d6f0652d-06e6-4da5-bf1b-e2865ff812b0" Type="Ort">
          <Name>Pavia</Name>
        </Entitaet>
        <Entitaet Id="310f7087-28ed-4088-9927-80b9b0c985cd" Type="Person">
          <Name>Kalif Harun al-Raschid</Name>
        </Entitaet>
        <Entitaet Id="c69e1840-0bc0-4cff-8084-4702fa128a15" Type="Ort">
          <Name>Pisa</Name>
        </Entitaet>
        <Entitaet Id="fde96c5c-f2ea-4699-a5b3-814f92e2bb6f" Type="Ort">
          <Name>Vercelli</Name>
        </Entitaet>
        <Entitaet Id="9eaf22f9-fc67-4ec7-a09d-ff1a4c04a63e" Type="Ort">
          <Name>Ivrea</Name>
        </Entitaet>
        <Entitaet Id="ba80122a-4252-4873-8bf3-70e81768f5cb" Type="Ort">
          <Name>Afrika</Name>
        </Entitaet>
        <Entitaet Id="00fee83e-1f5a-4d79-8d9e-89334e61a9c6" Type="Person">
          <Name>Abul Abaz</Name>
        </Entitaet>
        <Entitaet Id="3e9ca6a5-4860-45ff-be26-49bb12879dfe" Type="Ort">
          <Name>Gallien</Name>
        </Entitaet>
      </Entitaeten>
    </Quelle>
    <Quelle>
      <QuellenId>0007</QuellenId>
      <Zitation>Annales Tiliani pars altera 801 (802), ed. Pertz 1826, S. 223.</Zitation>
      <ZeitangabeQuelle>801 (802)</ZeitangabeQuelle>
      <Inhaltsangabe>Die Stadt Barcelona in Spanien wird 801 (802) [801-803] geplündert, nachdem sie zwei Jahre belagert worden war. Sa’dun al-Ru’aini, der Statthalter von Barcelona, und andere Sarazenen werden gefangen genommen. Auch in Italien wird eine Stadt, Chieti, erobert und niedergebrannt. Sa’dun al-Ru’aini wird (zusammen mit dem italienischen Statthalter Chietis, Roselmus) Kaiser Karl I. dem Großen vorgeführt und verbannt.</Inhaltsangabe>
      <VolltextOriginalsprache>Ipsa civitate rapta est Barcinona [Barcelona] in Hispania [Spanien] biennio obsessa. Zatun praefectus [Sa’dun al-Ru’aini] eius et alii plures Saraceni comprehensi: et in Italia [Italien] Teata [Chieti] civitas similiter capta incensa est. Zatun et Roselmus una die ad praesentiam imperatoris deducti, exilio damnati sunt.</VolltextOriginalsprache>
      <VolltextUebersetzung>-</VolltextUebersetzung>
      <ZitationUebersetzung>-</ZitationUebersetzung>
      <ZeitangabeWissenschaft>
        <Datum Text="801-803" From="801-01-01" To="803-12-31" />
      </ZeitangabeWissenschaft>
      <Berichtszeitraum>
        <Datum Text="800-810" From="800-01-01" To="810-12-31" />
      </Berichtszeitraum>
      <Abfassungszeitraum />
      <GeographischesStichwort>
        <Ort>Iberische Halbinsel (Spanien, Portugal)</Ort>
        <Ort>Barcelona</Ort>
      </GeographischesStichwort>
      <Beteiligte>
        <Beteiligter>sI</Beteiligter>
        <Beteiligter>sK</Beteiligter>
        <Beteiligter>aI</Beteiligter>
      </Beteiligte>
      <Interaktion>j</Interaktion>
      <Auffaelligkeiten>
        <Schlagwort>Eroberung</Schlagwort>
        <Schlagwort>Plünderung</Schlagwort>
        <Schlagwort>Gefangennahme</Schlagwort>
        <Schlagwort>Verbannung</Schlagwort>
      </Auffaelligkeiten>
      <Suchbegriffe>
        <Suchwort>Saracenus</Suchwort>
        <Suchwort>Sarazenen</Suchwort>
        <Suchwort>Hispania</Suchwort>
        <Suchwort>Spanien</Suchwort>
        <Suchwort>Barcinona</Suchwort>
        <Suchwort>Barcelona</Suchwort>
        <Suchwort>Africanus</Suchwort>
        <Suchwort>Afrika</Suchwort>
      </Suchbegriffe>
      <Anmerkungen>Vgl. für das Ereignis RI I, 374e.
Zur zeitlich nicht klar belegbaren Eroberung Barcelonas durch Ludwig I. den Frommen vgl. ausführlich Egon Boshof, Ludwig der Fromme, Darmstadt 1996, S. 74-77.
Die Jahresangaben in runden Klammern beziehen sich wohl auf Unterschiede in der handschriftlichen Überlieferung, wie sie die Ausgabe von Andrea Chesnio vermittelt, vgl. Annales Tiliani, ed. Georg Heinrich Pertz, in: MGH SS 1, Hannover 1826, S. 220. Die handschriftliche Überlieferung ist verloren.</Anmerkungen>
      <Entitaeten>
        <Entitaet Id="75089f58-05c5-4d54-a13e-3adb94ba8635" Type="Ort">
          <Name>Barcelona</Name>
        </Entitaet>
        <Entitaet Id="1b3bc365-6179-45d1-b0bd-21aab4abd3e3" Type="Ort">
          <Name>Spanien</Name>
        </Entitaet>
        <Entitaet Id="08940327-0bb7-4b38-bbf6-3965d86ee28e" Type="Person">
          <Name>Sa’dun al-Ru’aini</Name>
        </Entitaet>
        <Entitaet Id="650b43d3-3751-4410-a116-9bafde2cfb82" Type="Ort">
          <Name>Italien</Name>
        </Entitaet>
        <Entitaet Id="abfb9a3b-1810-4309-9683-be45f7e2ad8f" Type="Ort">
          <Name>Chieti</Name>
        </Entitaet>
      </Entitaeten>
    </Quelle>
  </Quellen>
</ParsedDocxDocument>